{
  "version": "v6.7.17",
  "fixed": [
    "CITTA！今天有炸 -> CITTA！義式冰淇淋專門店",
    "分類 小吃/美式 -> 咖啡甜點",
    "移除炸物/宵夜描述與炸物標籤",
    "地圖搜尋改成 CITTA 義式冰淇淋 嘉義市"
  ],
  "counts": {
    "燒肉": 18,
    "日式": 73,
    "咖哩": 22,
    "異國料理": 28,
    "小吃": 159,
    "咖啡甜點": 45,
    "中式": 125,
    "美式": 17,
    "火鍋": 32,
    "雞肉飯": 26,
    "早餐": 28,
    "燒烤": 11,
    "宵夜": 17,
    "酒吧": 17,
    "鐵板燒": 16,
    "義式": 17,
    "熱炒": 20,
    "素食": 16,
    "飲料": 1,
    "海鮮": 3,
    "居酒屋": 1,
    "麵食": 1,
    "鍋燒": 1,
    "泰式": 1
  },
  "notes": [
    "已用餐廳資料表掃過甜點、炸物、宵夜/酒吧關鍵字；沒有再看到像 CITTA 這種明顯把甜點店放成炸物的錯誤。",
    "阿娥豆花、一銀仙草目前仍在小吃分類；如果想讓甜點更完整，下一版可一併加入咖啡甜點。"
  ]
}